flake8_stash/__init__.py
flake8_stash/dunder_all.py
flake8_stash/issues.py
flake8_stash/plugin.py
flake8_stash-0.11.0.dist-info/entry_points.txt
flake8_stash-0.11.0.dist-info/licenses/LICENSE
flake8_stash-0.11.0.dist-info/WHEEL
flake8_stash-0.11.0.dist-info/METADATA
flake8_stash-0.11.0.dist-info/RECORD
