Metadata-Version: 2.4
Name: flake8-stash
Version: 0.11.0
Summary: A collection of flake8 checks.
Keywords: flake8,flake8 plugin,collection of checks,lint dunder all
Author: Ghazi Abbassi
Requires-Python: >=3.8
Classifier: Intended Audience :: Developers
Classifier: License :: OSI Approved :: MIT License
Classifier: Programming Language :: Python :: 3
Classifier: Programming Language :: Python :: 3.8
Classifier: Programming Language :: Python :: 3.9
Classifier: Programming Language :: Python :: 3.10
Classifier: Programming Language :: Python :: 3.11
Classifier: Programming Language :: Python :: 3.12
Classifier: Programming Language :: Python :: 3.13
Classifier: Programming Language :: Python :: 3.14
License-File: LICENSE
Requires-Dist: flake8
Requires-Dist: pre-commit ; extra == "dev"
Requires-Dist: flit ; extra == "release"
Requires-Dist: keyring ; extra == "release"
Requires-Dist: tbump ; extra == "release"
Requires-Dist: pytest ; extra == "test"
Requires-Dist: pre-commit ; extra == "test"
Project-URL: Changelog, https://github.com/ghazi-git/flake8-stash/releases
Project-URL: Code, https://github.com/ghazi-git/flake8-stash
Project-URL: Issues, https://github.com/ghazi-git/flake8-stash/issues
Provides-Extra: dev
Provides-Extra: release
Provides-Extra: test
